python_package_importer/__init__.py
python_package_importer/_compatibility.py
python_package_importer/importer.py
python_package_importer/object_finder.py
python_package_importer/pytest.py
python_package_importer-1.0.dist-info/LICENSE
python_package_importer-1.0.dist-info/METADATA
python_package_importer-1.0.dist-info/WHEEL
python_package_importer-1.0.dist-info/top_level.txt
python_package_importer-1.0.dist-info/RECORD
