Metadata-Version: 2.1
Name: python-package-importer
Version: 1.0
Summary: Dynamically import all python files in a directory.
Home-page: https://github.com/MichaelKim0407/python-package-importer
Author: Michael Kim
Author-email: mkim0407@gmail.com
License: MIT
Classifier: Intended Audience :: Developers
Classifier: Development Status :: 5 - Production/Stable
Classifier: License :: OSI Approved :: MIT License
Classifier: Programming Language :: Python
Classifier: Programming Language :: Python :: 3
Classifier: Programming Language :: Python :: 3.7
Classifier: Programming Language :: Python :: 3.8
Classifier: Programming Language :: Python :: 3.9
Classifier: Programming Language :: Python :: 3.10
Classifier: Programming Language :: Python :: 3.11
Classifier: Topic :: Software Development :: Libraries :: Python Modules
License-File: LICENSE
Requires-Dist: returns-decorator
Provides-Extra: cached-property
Requires-Dist: cached-property ; extra == 'cached-property'
Provides-Extra: ci
Requires-Dist: flake8 ; extra == 'ci'
Requires-Dist: flake8-commas ; extra == 'ci'
Requires-Dist: flake8-quotes ; extra == 'ci'
Requires-Dist: flake8-multiline-containers ; extra == 'ci'
Requires-Dist: pytest ; extra == 'ci'
Requires-Dist: pytest-cov ; extra == 'ci'
Requires-Dist: coveralls ; extra == 'ci'
Provides-Extra: dev
Requires-Dist: flake8 ; extra == 'dev'
Requires-Dist: flake8-commas ; extra == 'dev'
Requires-Dist: flake8-quotes ; extra == 'dev'
Requires-Dist: flake8-multiline-containers ; extra == 'dev'
Requires-Dist: pytest ; extra == 'dev'
Requires-Dist: pytest-cov ; extra == 'dev'
